LICENSE
MANIFEST.in
README.rst
setup.py
django_pydenticon/__init__.py
django_pydenticon/admin.py
django_pydenticon/models.py
django_pydenticon/settings.py
django_pydenticon/tests.py
django_pydenticon/urls.py
django_pydenticon/views.py
django_pydenticon.egg-info/PKG-INFO
django_pydenticon.egg-info/SOURCES.txt
django_pydenticon.egg-info/dependency_links.txt
django_pydenticon.egg-info/requires.txt
django_pydenticon.egg-info/top_level.txt
docs/Makefile
docs/about.rst
docs/apireference.rst
docs/conf.py
docs/configuration.rst
docs/index.rst
docs/installation.rst
docs/make.bat
docs/privacy.rst
docs/releasenotes.rst
docs/usage.rst